django_migrations_graph-0.1.1.dist-info/DESCRIPTION.rst
django_migrations_graph-0.1.1.dist-info/METADATA
django_migrations_graph-0.1.1.dist-info/RECORD
django_migrations_graph-0.1.1.dist-info/WHEEL
django_migrations_graph-0.1.1.dist-info/metadata.json
django_migrations_graph-0.1.1.dist-info/top_level.txt
migraph/__init__.py
migraph/apps.py
migraph/management/__init__.py
migraph/management/commands/__init__.py
migraph/management/commands/migration_dependencies.py
