Metadata-Version: 2.0
Name: django-migrations-graph
Version: 0.1.1
Summary: Django-admin command to display migrations with dependencies.
Home-page: https://github.com/dizballanze/django-migrations-graph
Author: Iurii Shikanov
Author-email: dizballanze@gmail.com
License: MIT
Keywords: django-migrations-graph
Platform: UNKNOWN
Classifier: Development Status :: 3 - Alpha
Classifier: Framework :: Django
Classifier: Framework :: Django :: 1.8
Classifier: Framework :: Django :: 1.9
Classifier: Framework :: Django :: 1.10
Classifier: Framework :: Django :: 1.11
Classifier: Intended Audience :: Developers
Classifier: License :: OSI Approved :: BSD License
Classifier: Natural Language :: English
Classifier: Programming Language :: Python :: 2
Classifier: Programming Language :: Python :: 2.7
Classifier: Programming Language :: Python :: 3
Classifier: Programming Language :: Python :: 3.4
Classifier: Programming Language :: Python :: 3.5
Requires-Dist: Django (>=1.7)
